wesync/__about__.py
wesync/__init__.py
wesync/__main__.py
wesync/wesync.py
wesync/commands/__init__.py
wesync/commands/commandFactory.py
wesync/commands/commandManager.py
wesync/commands/operationManager.py
wesync/commands/backup/__init__.py
wesync/commands/backup/backupCommand.py
wesync/commands/backup/backupExport.py
wesync/commands/backup/backupImport.py
wesync/commands/backup/backupList.py
wesync/commands/backup/backupPull.py
wesync/commands/backup/backupPush.py
wesync/commands/config/__init__.py
wesync/commands/config/configCommand.py
wesync/commands/config/configCommit.py
wesync/commands/config/configInit.py
wesync/commands/config/configPurge.py
wesync/commands/config/configUpdate.py
wesync/commands/deployment/__init__.py
wesync/commands/deployment/deploymentAdd.py
wesync/commands/deployment/deploymentCommand.py
wesync/commands/deployment/deploymentDelete.py
wesync/commands/deployment/deploymentList.py
wesync/commands/snapshot/__init__.py
wesync/commands/snapshot/snapshotCommand.py
wesync/commands/snapshot/snapshotDelete.py
wesync/commands/snapshot/snapshotExport.py
wesync/commands/snapshot/snapshotImport.py
wesync/commands/snapshot/snapshotList.py
wesync/commands/snapshot/snapshotPurge.py
wesync/commands/sync/__init__.py
wesync/commands/sync/syncCommand.py
wesync/commands/version/__init__.py
wesync/commands/version/versionCommand.py
wesync/common/__init__.py
wesync/common/arguments.py
wesync/common/logging.py
wesync/services/__init__.py
wesync/services/deploymentSyncService.py
wesync/services/initializationService.py
wesync/services/projectManagerFactory.py
wesync/services/snapshot.py
wesync/services/snapshotService.py
wesync/services/backup/backupService.py
wesync/services/config/__init__.py
wesync/services/config/configManager.py
wesync/services/config/configSync.py
wesync/services/config/localConfig.py
wesync/services/config/localConfigManager.py
wesync/services/config/remoteConfig.py
wesync/services/config/resolvers/__init__.py
wesync-0.0.4.post3.dist-info/METADATA
wesync-0.0.4.post3.dist-info/WHEEL
wesync-0.0.4.post3.dist-info/entry_points.txt
wesync-0.0.4.post3.dist-info/licenses/LICENSE
wesync-0.0.4.post3.dist-info/RECORD
