Metadata-Version: 2.1
Name: wesync
Version: 0.0.4.post3
Summary: Deployment synchronization tool
Author-email: Sysadmin <sysadmin@welink.ro>
License-File: LICENSE
Classifier: License :: OSI Approved :: MIT License
Classifier: Operating System :: OS Independent
Classifier: Programming Language :: Python :: 3
Requires-Python: >=3.7
